.DS_Store
setup.py
pycecream/__init__.py
pycecream/__init__.pyc
pycecream/cream_f90.f90
pycecream/cream_f90_220919.f90
pycecream/cream_old_f90.f90
pycecream/cream_trace.py
pycecream/creaminpar.par
pycecream.egg-info/PKG-INFO
pycecream.egg-info/SOURCES.txt
pycecream.egg-info/dependency_links.txt
pycecream.egg-info/not-zip-safe
pycecream.egg-info/requires.txt
pycecream.egg-info/top_level.txt
pycecream/.idea/encodings.xml
pycecream/.idea/misc.xml
pycecream/.idea/modules.xml
pycecream/.idea/pycecream.iml
pycecream/.idea/vcs.xml
pycecream/.idea/workspace.xml
pycecream/.idea/libraries/R_User_Library.xml
pycecream/__pycache__/__init__.cpython-37.pyc