Metadata-Version: 1.0
Name: pycecream
Version: 1.3.2
Summary: python implementation of the cream accretion disc fitting code https://academic.oup.com/mnras/article-abstract/456/2/1960/1066664?redirectedFrom=PDF
Home-page: https://github.com/dstarkey23/pycecream
Author: dstarkey23
Author-email: ds207@st-andrews.ac.uk
License: MIT
Platform: UNKNOWN
